Workbook

Sheet README
B2: NeuronOS — AI Unit Economics Model
B3: How to use this workbook
B5: 1. Go to the 'Assumptions' tab.
B6: 2. Every BLUE cell is an input you can change. Yellow-filled cells are the most important levers.
B7: 3. Fill in real, current LLM pricing (per 1M tokens) in the 'Model Pricing' section — the pricing shown is a placeholder starting point, not a live quote.
B8: 4. Set the customer profile (org size, monthly usage volumes) to match a real or hypothesized target customer.
B9: 5. Set your monthly subscription price hypothesis at the bottom of Assumptions.
B10: 6. Open the 'Cost Model' tab to see the per-feature cost breakdown computed from your inputs.
B11: 7. Open the 'Summary' tab for the bottom line: total AI cost per organization per month vs. your price, gross margin $ and %, and a chart of where the cost concentrates.
B12: 8. Everything recalculates automatically when you change an Assumptions cell — there are no hardcoded results anywhere in Cost Model or Summary.
B14: Color legend
B15: Blue text = input you should edit
... B21: Model pricing (per-1M-token rates) and default token-count assumptions in this workbook are placeholder starting points supplied for structure, not verified current prices — LLM provider pricing changes frequently. Replace every blue pricing cell in Assumptions with pricing pulled directly from the relevant provider's current pricing page before treating any output number as a real decision input.

Sheet Assumptions
B2: Assumptions & Inputs
B3: Edit every blue cell. Yellow-filled cells are the highest-leverage assumptions to get right.
B5: 1. Target Customer Profile
B6: Field | C6: Value | D6: Unit | E6: Notes
B7: Active users in org | C7: 8 | D7: users | E7: Seats actively using the product
B8: Customers/accounts tracked | C8: 60 | D8: records | E8: Rows in the Customers module for this org
B9: Projects tracked | C9: 12 | D9: records
B10: Documents uploaded per month | C10: 25 | D10: docs/mo | E10: New + updated documents
B11: Avg pages per document | C11: 6 | D11: pages | E11: Drives chunk count
B12: Chat messages sent per month | C12: 300 | D12: msgs/mo | E12: AI Workspace usage — the biggest lever
B13: Meetings per month | C13: 20 | D13: meetings/mo
B14: Avg meeting transcript length | C14: 4500 | D14: words | E14: 0 if no transcript captured (manual notes only)
B15: AI Actions suggested per month | C15: 80 | D15: actions/mo | E15: Drafted follow-ups, briefs, etc.
B17: 2. Model Pricing (per 1,000,000 tokens, USD)
B18: Field | C18: Value | D18: Unit | E18: Notes
B19: Cheap/fast model — input | C19: 0.25 | D19: $/1M tok | E19: Used for: embedding-adjacent extraction, classification
B20: Cheap/fast model — output | C20: 1.25 | D20: $/1M tok
B21: Frontier/reasoning model — input | C21: 3 | D21: $/1M tok | E21: Used for: chat, drafting, summarization, briefs
B22: Frontier/reasoning model — output | C22: 15 | D22: $/1M tok
B23: Embedding model | C23: 0.02 | D23: $/1M tok | E23: Used for: document chunk embeddings
B24: PLACEHOLDER RATES — replace with current pricing from provider pricing pages before relying on this model.
B26: 3. Token Assumptions per Event
B27: Field | C27: Value | D27: Unit | E27: Notes
B28: Chunks per page | C28: 2 | D28: chunks/pg | E28: ~500-token semantic chunks
B29: Tokens per chunk (for embedding) | C29: 500 | D29: tokens
B30: Doc summarization — input tokens/doc | C30: 3000 | D30: tokens | E30: Full doc text fed to summarizer, scales with pages
B31: Doc summarization — output tokens/doc | C31: 250 | D31: tokens | E31: AI Summary length
B32: Chat — input tokens/message | C32: 3500 | D32: tokens | E32: Question + RAG-retrieved context + recent history — often much larger than the visible question
B33: Chat — output tokens/message | C33: 400 | D33: tokens
B34: Meeting brief — input tokens | C34: 2000 | D34: tokens | E34: Related context: customer summary, docs, prior meetings
B35: Meeting brief — output tokens | C35: 350 | D35: tokens
B36: Meeting summarization — input tokens per word of transcript | C36: 1.4 | D36: tokens/word | E36: Rough word-to-token ratio
B37: Meeting summarization — output tokens | C37: 400 | D37: tokens | E37: Summary + extracted action items
B38: AI Action draft — input tokens | C38: 1500 | D38: tokens | E38: Context injection: customer/project state
B39: AI Action draft — output tokens | C39: 300 | D39: tokens | E39: Drafted email/task/report
B41: 4. Pricing Hypothesis
B42: Field | C42: Value | D42: Unit | E42: Notes
B43: Monthly subscription price per organization | C43: 99 | D43: $/mo | E43: Your hypothesized SMB plan price — change this to test different price points
B44: Non-AI infra cost per org per month (hosting, storage, misc.) | C44: 8 | D44: $/mo | E44: Rough estimate — DB, Redis, R2 storage, background workers

Sheet Cost Model
B2: Monthly AI Cost by Feature
B3: All cells below are formulas pulling from the Assumptions tab — change assumptions there, this recalculates.
B5: Feature | C5: Monthly Volume | D5: Input Cost ($) | E5: Output Cost ($) | F5: Total Cost ($) | G5: Formula basis
B6: Document embedding | C6: =Assumptions!$C$10*Assumptions!$C$11*Assumptions!$C$28 -> 300 | D6: =C6*(Assumptions!$C$29)/1000000*Assumptions!$C$23 -> 0.003 | E6: =C6*(0)/1000000*Assumptions!$C$23 -> 0 | F6: =D6+E6 -> 0.003 | G6: Volume = docs/mo × avg pages × chunks/page. Embeddings have no output tokens.
B7: Document summarization | C7: =Assumptions!$C$10 -> 25 | D7: =C7*(Assumptions!$C$30)/1000000*Assumptions!$C$21 -> 0.225 | E7: =C7*(Assumptions!$C$31)/1000000*Assumptions!$C$22 -> 0.09375 | F7: =D7+E7 -> 0.31875 | G7: One summarization call per uploaded document, frontier model.
B8: AI Workspace chat | C8: =Assumptions!$C$12 -> 300 | D8: =C8*(Assumptions!$C$32)/1000000*Assumptions!$C$21 -> 3.15 | E8: =C8*(Assumptions!$C$33)/1000000*Assumptions!$C$22 -> 1.8 | F8: =D8+E8 -> 4.95 | G8: One call per chat message. Input includes RAG-retrieved context + history, not just the question.
B9: Meeting briefs | C9: =Assumptions!$C$13 -> 20 | D9: =C9*(Assumptions!$C$34)/1000000*Assumptions!$C$21 -> 0.12 | E9: =C9*(Assumptions!$C$35)/1000000*Assumptions!$C$22 -> 0.105 | F9: =D9+E9 -> 0.225 | G9: One pre-meeting brief generated per meeting.
B10: Meeting summarization | C10: =Assumptions!$C$13 -> 20 | D10: =C10*(Assumptions!$C$14*Assumptions!$C$36)/1000000*Assumptions!$C$21 -> 0.378 | E10: =C10*(Assumptions!$C$37)/1000000*Assumptions!$C$22 -> 0.12 | F10: =D10+E10 -> 0.498 | G10: Input tokens scale with transcript length (words × tokens/word ratio).
B11: AI Action drafting | C11: =Assumptions!$C$15 -> 80 | D11: =C11*(Assumptions!$C$38)/1000000*Assumptions!$C$21 -> 0.36 | E11: =C11*(Assumptions!$C$39)/1000000*Assumptions!$C$22 -> 0.36 | F11: =D11+E11 -> 0.72 | G11: One generation call per suggested AI Action (follow-up email, task, etc.).
B12: Total AI Cost per Organization / Month | F12: =SUM(F6:F11) -> 6.71475

Sheet Summary
B2: Unit Economics Summary
B3: The bottom line — does the AI cost per organization leave room for a healthy margin at your price?
B5: Metric | C5: Value | D5: Notes
B6: Monthly subscription price | C6: =Assumptions!$C$43 -> 99 | D6: From Assumptions § 4
B7: Total AI (LLM) cost per org / month | C7: ='Cost Model'!$F$12 -> 6.71475 | D7: From Cost Model total row
B8: Non-AI infra cost per org / month | C8: =Assumptions!$C$44 -> 8 | D8: From Assumptions § 4
B9: Total cost per org / month (AI + infra) | C9: =C7+C8 -> 14.71475 | D9: Sum of the two rows above
B11: Gross margin ($/mo) | C11: =C6-C9 -> 84.28525 | D11: Price minus total cost
B12: Gross margin (%) | C12: =IFERROR(C11/C6,0) -> 0.85136616 | D12: Gross margin as a percentage of price
B13: AI cost as % of price | C13: =IFERROR(C7/C6,0) -> 0.067825758 | D13: The single most important number in this sheet — if this is high, usage caps or model routing matter a lot
B16: Cost Breakdown by Feature
B17: Feature | C17: Monthly Cost ($) | D17: % of Total AI Cost
B18: ='Cost Model'!B6 -> Document embedding | C18: ='Cost Model'!F6 -> 0.003 | D18: =IFERROR(C18/$C$7,0) -> 0.00044677762
B19: ='Cost Model'!B7 -> Document summarization | C19: ='Cost Model'!F7 -> 0.31875 | D19: =IFERROR(C19/$C$7,0) -> 0.047470122
B20: ='Cost Model'!B8 -> AI Workspace chat | C20: ='Cost Model'!F8 -> 4.95 | D20: =IFERROR(C20/$C$7,0) -> 0.73718307
B21: ='Cost Model'!B9 -> Meeting briefs | C21: ='Cost Model'!F9 -> 0.225 | D21: =IFERROR(C21/$C$7,0) -> 0.033508321
B22: ='Cost Model'!B10 -> Meeting summarization | C22: ='Cost Model'!F10 -> 0.498 | D22: =IFERROR(C22/$C$7,0) -> 0.074165084
B23: ='Cost Model'!B11 -> AI Action drafting | C23: ='Cost Model'!F11 -> 0.72 | D23: =IFERROR(C23/$C$7,0) -> 0.10722663
B25: How to read this sheet
B26: Gross margin ($/mo) and (%) reflect AI + infra cost only — they do not include sales, support, or your own time; treat this as an upper bound on true margin, not the full P&L.
B27: 'AI cost as % of price' is the single most useful sanity check: if AI alone eats a large share of the subscription price, there is very little room left for anything else, and usage-based plan tiers or model routing (cheaper models for lower-stakes tasks) become urgent rather than optional.
B28: Chat is very likely to be the largest and most volatile cost line, because unlike the other features it has no natural cap — a highly engaged user can send far more messages than a typical one. Consider whether a message allowance per plan tier is warranted once real usage data exists.
B29: Re-run this model whenever: (a) you get real usage data from design partners instead of estimates, (b) provider pricing changes, or (c) you change which model tier a feature uses.
